Metadata-Version: 2.1
Name: serdeserf
Version: 0.1
Summary: don't use it, even if you have to
Author-email: kirkat6@gmail.com
